axiomlib/__init__.py
axiomlib/axiom.py
axiomlib/calculate.py
axiomlib/weightCalculate.py
axiomlib-0.1.0.dist-info/METADATA
axiomlib-0.1.0.dist-info/WHEEL
axiomlib-0.1.0.dist-info/top_level.txt
axiomlib-0.1.0.dist-info/RECORD
